manheim_c7n_tools/__init__.py
manheim_c7n_tools/config.py
manheim_c7n_tools/dryrun_diff.py
manheim_c7n_tools/errorscan.py
manheim_c7n_tools/notifyonly.py
manheim_c7n_tools/policygen.py
manheim_c7n_tools/runner.py
manheim_c7n_tools/s3_archiver.py
manheim_c7n_tools/utils.py
manheim_c7n_tools/version.py
manheim_c7n_tools/tests/__init__.py
manheim_c7n_tools/tests/test_config.py
manheim_c7n_tools/tests/test_notifyonly.py
manheim_c7n_tools/tests/test_policygen.py
manheim_c7n_tools/tests/test_runner.py
manheim_c7n_tools/tests/test_utils.py
manheim_c7n_tools/tests/test_version.py
manheim_c7n_tools/vendor/__init__.py
manheim_c7n_tools/vendor/mugc.py
manheim_c7n_tools-1.4.3.dist-info/LICENSE
manheim_c7n_tools-1.4.3.dist-info/METADATA
manheim_c7n_tools-1.4.3.dist-info/WHEEL
manheim_c7n_tools-1.4.3.dist-info/entry_points.txt
manheim_c7n_tools-1.4.3.dist-info/top_level.txt
manheim_c7n_tools-1.4.3.dist-info/RECORD
