Metadata-Version: 2.1
Name: manheim-c7n-tools
Version: 1.4.3
Summary: c7n policy generation script and related utilities
Home-page: https://github.com/manheim/manheim-c7n-tools
Author: Manheim Release Engineering
Author-email: man-releaseengineering@manheim.com
License: UNKNOWN
Keywords: custodian aws c7n policy
Platform: UNKNOWN
Classifier: Development Status :: 5 - Production/Stable
Classifier: Environment :: Console
Classifier: Intended Audience :: Developers
Classifier: Intended Audience :: Information Technology
Classifier: Intended Audience :: System Administrators
Classifier: License :: OSI Approved :: Apache Software License
Classifier: Natural Language :: English
Classifier: Operating System :: OS Independent
Classifier: Programming Language :: Python :: 2.7
Classifier: Programming Language :: Python :: 3
Classifier: Topic :: System :: Distributed Computing
Classifier: Topic :: System :: Systems Administration
Classifier: Topic :: Utilities
License-File: LICENSE
Requires-Dist: boto3
Requires-Dist: botocore
Requires-Dist: docutils
Requires-Dist: tabulate (<0.9.0,>=0.8.0)
Requires-Dist: pyyaml
Requires-Dist: c7n (==0.9.16)
Requires-Dist: c7n-mailer (==0.6.15)
Requires-Dist: sphinx
Requires-Dist: sphinx-rtd-theme
Requires-Dist: m2r2
Requires-Dist: mistune (==0.8.4)
